[{"keyId":37980,"srcId":105831,"issued":"深圳市气象台","issuer":"王书欣","issueTime":"2026-07-08 04:35:07","eventCategory":"自然灾害","subCategory":"气象灾害.雷雨大风","wLevel":"黄色","sysnum":"分区预警","startTime":"2026-07-08 04:33:00","area":"海山、盐田、梅沙、松岗、福永、沙井、航城、福海、新桥、燕罗、公明、马田、马峦、碧岭、石井、大鹏新区、珠江口、大鹏湾","matter":"【深圳市分区雷雨大风黄色预警信号】深圳市气象台2026年07月08日04时33分发布大鹏新区、珠江口、大鹏湾、盐田区（海山、盐田、梅沙街道）、宝安区（松岗、福永、沙井、航城、福海、新桥、燕罗街道）、光明区（公明、马田街道）和坪山区（马峦、碧岭、石井街道）雷雨大风黄色预警信号，预计1-2小时有雷雨，并伴有8级左右短时大风和强雷电。请落实各项防风防雨防雷电措施。","developments":"","wmeasures":"","tel":"","crtTime":"2026-07-08 04:35:16","confirmTime":"2026-07-08 04:35:07","life":true},{"keyId":37979,"srcId":20004,"issued":"深汕特别合作区","issuer":"吴道远","issueTime":"2026-07-08 03:54","eventCategory":"自然灾害","subCategory":"雷雨大风","wLevel":"黄色","sysnum":"分区预警","startTime":"2026-07-08 03:54:00","area":"小漠、鲘门、鹅埠、赤石、深汕海域","matter":"【深汕特别合作区发布雷雨大风黄色预警信号】 深圳市气象台2026年07月08日03时54分在深汕特别合作区、深汕海域发布雷雨大风黄色预警信号，预计1-2小时内深汕区将出现强雷雨天气，并伴有8级左右短时大风。请落实各项防风防雷电措施。","developments":"","wmeasures":"","tel":"","crtTime":"2026-07-08 03:57:00","confirmTime":"2026-07-08 03:54:00","life":true},{"keyId":37976,"srcId":0,"issued":"深圳市规划和自然资源局","issuer":"张洪岩","issueTime":"2026-07-07 21:00:00","eventCategory":"自然灾害","subCategory":"地质灾害","wLevel":"黄色","sysnum":"深圳市地质灾害气象风险监测预警平台","startTime":"2026-07-07 21:00:00","area":"黄贝、东湖、莲塘、南山、桃源、西丽、宝安区、坂田、龙华区、坑梓、石井、龙田、光明区、大鹏新区","matter":"【深圳市地质灾害气象风险预警2026年第22号】根据目前降雨情况，结合我市地质环境条件，现对宝安区、龙华区、光明区、大鹏新区、罗湖区（黄贝、东湖、莲塘街道）、南山区（南山、桃源、西丽街道）、龙岗区（坂田街道）、坪山区（坑梓、石井、龙田街道）发布地质灾害气象风险黄色预警，请相关部门和单位做好防御工作。市规划和自然资源局与市气象局2026年07月07日21时联合发布，有效期至2026年07月08日21时。","developments":"","wmeasures":"","tel":"82946959","crtTime":"2026-07-07 21:10:36","confirmTime":"2026-07-07 21:11:42","life":true},{"keyId":37972,"srcId":0,"issued":"深圳市规划和自然资源局","issuer":"张洪岩","issueTime":"2026-07-07 15:00:00","eventCategory":"自然灾害","subCategory":"地质灾害","wLevel":"黄色","sysnum":"深圳市地质灾害气象风险监测预警平台","startTime":"2026-07-07 15:00:00","area":"黄贝、东湖、莲塘、桃源、新安、西乡、福永、石岩、坂田、龙华区、坑梓、石井、龙田、光明、新湖、凤凰、大鹏新区","matter":"【深圳市地质灾害气象风险预警2026年第21号】根据目前降雨情况，结合我市地质环境条件，现对龙华区、大鹏新区、罗湖区（黄贝、东湖、莲塘街道）、南山区（桃源街道）、宝安区（新安、西乡、福永、石岩街道）、龙岗区（坂田街道）、坪山区（坑梓、石井、龙田街道）、光明区（光明、新湖、凤凰街道）发布地质灾害气象风险黄色预警，请相关部门和单位做好防御工作。市规划和自然资源局与市气象局2026年07月07日15时联合发布，有效期至2026年07月08日15时。","developments":"","wmeasures":"","tel":"82946959","crtTime":"2026-07-07 14:41:05","confirmTime":"2026-07-07 14:47:56","life":true},{"keyId":37966,"srcId":0,"issued":"深圳市规划和自然资源局","issuer":"张洪岩","issueTime":"2026-07-07 09:00:00","eventCategory":"自然灾害","subCategory":"地质灾害","wLevel":"黄色","sysnum":"深圳市地质灾害气象风险监测预警平台","startTime":"2026-07-07 09:00:00","area":"黄贝、东湖、莲塘、新安、西乡、坂田、观澜、坑梓、石井、龙田、大鹏新区","matter":"【深圳市地质灾害气象风险预警2026年第20号】根据目前降雨情况，结合我市地质环境条件，现对大鹏新区、罗湖区（黄贝、东湖、莲塘街道）、宝安区（新安、西乡街道）、龙岗区（坂田街道）、龙华区（观澜街道）、坪山区（坑梓、石井、龙田街道）发布地质灾害气象风险黄色预警，请相关部门和单位做好防御工作。市规划和自然资源局与市气象局2026年07月07日09时联合发布，有效期至2026年07月08日09时。","developments":"","wmeasures":"","tel":"82946959","crtTime":"2026-07-07 08:37:30","confirmTime":"2026-07-07 09:00:41","life":true}]